ghpolicy/cli.py
ghpolicy/main.py
ghpolicy/policy.py
ghpolicy/policies/default_branch.py
ghpolicy/policies/repository_settings.py
ghpolicy/policies/team_permission.py
ghpolicy/policies/topics.py
ghpolicy/policies/visibility.py
github_policies-0.2.0.dist-info/METADATA
github_policies-0.2.0.dist-info/WHEEL
github_policies-0.2.0.dist-info/entry_points.txt
github_policies-0.2.0.dist-info/top_level.txt
github_policies-0.2.0.dist-info/RECORD
