Metadata-Version: 2.1
Name: github-policies
Version: 0.2.0
Summary: Automate GitHub repository settings.
Author-email: Lab Digital <opensource@labdigital.nl>
License: Private
Requires-Python: >=3.11
Requires-Dist: PyGithub (>=1.58.1)
Requires-Dist: click (>=8.1.3)
Requires-Dist: PyYAML (>=6.0)
